{
	"backtrace" : 1,
	"backtraceGraph" : 
	{
		"commands" : 
		[
			"add_custom_target",
			"add_dependencies"
		],
		"files" : 
		[
			"llvm/test/CMakeLists.txt"
		],
		"nodes" : 
		[
			{
				"file" : 0
			},
			{
				"command" : 0,
				"file" : 0,
				"line" : 250,
				"parent" : 0
			},
			{
				"command" : 1,
				"file" : 0,
				"line" : 251,
				"parent" : 0
			}
		]
	},
	"dependencies" : 
	[
		{
			"backtrace" : 2,
			"id" : "check-all::@024f1ffc8678330252ec"
		}
	],
	"folder" : 
	{
		"name" : "Tests"
	},
	"id" : "check::@9506b079d60db5cecd5a",
	"name" : "check",
	"paths" : 
	{
		"build" : "llvm/test",
		"source" : "llvm/test"
	},
	"sources" : [],
	"type" : "UTILITY"
}
